santoku/__init__.py
santoku/aws/__init__.py
santoku/aws/s3.py
santoku/aws/secretsmanager.py
santoku/aws/sqs.py
santoku/aws/test/__init__.py
santoku/aws/test/test_s3.py
santoku/aws/test/test_secretsmanager.py
santoku/aws/test/test_sqs.py
santoku/aws/utils.py
santoku/exceptions.py
santoku/google/__init__.py
santoku/google/bigquery.py
santoku/google/test/__init__.py
santoku/google/test/test_bigquery.py
santoku/salesforce/__init__.py
santoku/salesforce/lightning.py
santoku/salesforce/test/__init__.py
santoku/salesforce/test/test_lightning.py
santoku/slack/__init__.py
santoku/slack/slackbot.py
santoku/slack/test/__init__.py
santoku/slack/test/test_slackbot.py
santoku/sql/__init__.py
santoku/sql/mysql.py
santoku/sql/test/__init__.py
santoku/sql/test/test_mysql.py
santoku/utils/README.md
santoku/utils/__init__.py
santoku/utils/configuration.py
santoku/utils/test/__init__.py
santoku/utils/test/test_configuration.py
santoku/utils/test/test_url_handler.py
santoku/utils/url_handler.py
santoku-221018.38.dist-info/LICENSE
santoku-221018.38.dist-info/WHEEL
santoku-221018.38.dist-info/METADATA
santoku-221018.38.dist-info/RECORD
