Metadata-Version: 2.1
Name: santoku
Version: 221018.38
Summary: Custom Python wrapper around many third party APIs, including AWS, BigQuery, Slack and Salesforce.
Home-page: https://github.com/wiris/santoku
License: MIT
Author: Data Science Team at WIRIS
Author-email: info@wiris.com
Requires-Python: >=3.9,<3.10
Classifier: Development Status :: 4 - Beta
Classifier: Framework :: Pytest
Classifier: Intended Audience :: Developers
Classifier: License :: OSI Approved :: MIT License
Classifier: Operating System :: OS Independent
Classifier: Programming Language :: Python :: 3
Classifier: Programming Language :: Python :: 3.9
Classifier: Topic :: Software Development :: Build Tools
Requires-Dist: boto3 (>=1.24.91,<2.0.0)
Requires-Dist: jsonschema (>=4.1.0,<5.0.0)
Requires-Dist: mysql-connector-python (>=8.0.5,<9.0.0)
Requires-Dist: pandas (>=1.2.4,<2.0.0)
Requires-Dist: pandas-gbq (>=0.17.1,<0.18.0)
Requires-Dist: requests (>=2.27.1,<3.0.0)
Requires-Dist: slackclient (>=2.5.0,<3.0.0)
Requires-Dist: tldextract (>=3.1.0,<4.0.0)
Project-URL: Repository, https://github.com/wiris/santoku
